churchsong/__init__.py
churchsong/__main__.py
churchsong/churchtools/__init__.py
churchsong/churchtools/events.py
churchsong/churchtools/song_statistics.py
churchsong/churchtools/song_verification.py
churchsong/configuration.py
churchsong/interactivescreen.py
churchsong/locales/de.po
churchsong/locales/messages.pot
churchsong/powerpoint/__init__.py
churchsong/powerpoint/appointments.py
churchsong/powerpoint/services.py
churchsong/songbeamer/__init__.py
churchsong/songbeamer/windows.py
churchsong/utils/__init__.py
churchsong/utils/date.py
churchsong/utils/progress.py
churchsong-0.10.16.dist-info/licenses/LICENSE
churchsong-0.10.16.dist-info/WHEEL
churchsong-0.10.16.dist-info/entry_points.txt
churchsong-0.10.16.dist-info/METADATA
churchsong-0.10.16.dist-info/RECORD
