Metadata-Version: 2.4
Name: ChurchSong
Version: 0.10.16
Summary: Download the event agenda from ChurchTool and instantiate a PowerPoint slide template with the names and portraits of service staff as well as song database verification.
Author: Stefan Bellon
License-Expression: MIT
License-File: LICENSE
Classifier: Programming Language :: Python :: 3
Classifier: Operating System :: Microsoft :: Windows
Classifier: Operating System :: POSIX :: Linux
Requires-Dist: click>=8.1.8
Requires-Dist: packaging>=25.0
Requires-Dist: platformdirs>=4.3.6
Requires-Dist: polib>=1.2.0
Requires-Dist: prettytable>=3.12.0
Requires-Dist: psutil>=6.1.0 ; sys_platform == 'win32'
Requires-Dist: pydantic>=2.9.2
Requires-Dist: pypdf>=6.1.1
Requires-Dist: python-pptx>=1.0.2
Requires-Dist: reportlab>=4.4.4
Requires-Dist: requests>=2.32.3
Requires-Dist: rich>=14.0.0
Requires-Dist: textual>=3.0.1
Requires-Dist: typer>=0.15.4
Requires-Dist: tzlocal>=5.3.1
Requires-Dist: xlsxwriter>=3.2.3
Requires-Python: >=3.14
Project-URL: Homepage, https://github.com/sbellon/ChurchSong
Project-URL: Repository, https://github.com/sbellon/ChurchSong.git
Project-URL: Changelog, https://github.com/sbellon/ChurchSong/blob/main/CHANGELOG.md
